sphinxnotes/recentupdate/__init__.py
sphinxnotes/recentupdate/meta.py
sphinxnotes/recentupdate/py.typed
sphinxnotes_recentupdate-1.0.dist-info/licenses/LICENSE
sphinxnotes_recentupdate-1.0.dist-info/METADATA
sphinxnotes_recentupdate-1.0.dist-info/WHEEL
sphinxnotes_recentupdate-1.0.dist-info/top_level.txt
sphinxnotes_recentupdate-1.0.dist-info/RECORD
